{
  "cities": [
    {
      "cityName": "Lisbon",
      "country": "Portugal",
      "emoji": "🇵🇹",
      "date": "2027-10-31T15:59:59.138Z",
      "notes": "My favorite city so far!",
      "position": {
        "lat": 38.727881642324164,
        "lng": -9.140900099907554
      },
      "id": "73930385"
    },
    {
      "cityName": "Madrid",
      "country": "Spain",
      "emoji": "🇪🇸",
      "date": "2027-07-15T08:22:53.976Z",
      "notes": "",
      "position": {
        "lat": 40.46635901755316,
        "lng": -3.7133789062500004
      },
      "id": "17806751"
    },
    {
      "cityName": "Berlin",
      "country": "Germany",
      "emoji": "🇩🇪",
      "date": "2027-02-12T09:24:11.863Z",
      "notes": "Amazing 😃",
      "position": {
        "lat": 52.53586782505711,
        "lng": 13.376933665713324
      },
      "id": "98443197"
    },
    {
      "id": "4eaf",
      "cityName": "Melbourne",
      "emoji": "🇦🇺",
      "date": "2024-02-27T05:10:29.069Z",
      "notes": "",
      "position": {
        "lat": "-37.81599613826919",
        "lng": "144.93919372558597"
      }
    },
    {
      "id": "d091",
      "cityName": "Chengdu",
      "emoji": "🇨🇳",
      "date": "2024-02-27T05:11:20.449Z",
      "notes": "",
      "position": {
        "lat": "30.584020180926487",
        "lng": "104.12841796875"
      }
    },
    {
      "id": "bc36",
      "cityName": "Beijing",
      "emoji": "🇨🇳",
      "date": "2024-02-27T05:18:39.056Z",
      "notes": "",
      "position": {
        "lat": "39.78145334904355",
        "lng": "116.19140625000001"
      }
    },
    {
      "id": "6186",
      "cityName": "Sastago",
      "emoji": "🇪🇸",
      "date": "2024-02-27T08:45:25.405Z",
      "notes": "",
      "position": {
        "lat": "41.376808565702355",
        "lng": "-0.37353515625000006"
      }
    },
    {
      "id": "8466",
      "cityName": "Shijiazhuang",
      "emoji": "🇨🇳",
      "date": "2024-02-27T08:45:43.822Z",
      "notes": "",
      "position": {
        "lat": "37.94419750075404",
        "lng": "114.4775390625"
      }
    }
  ]
}